adjutant/__init__.py
adjutant/adjutant_client.py
adjutant_discord-0.1.2.dist-info/LICENSE
adjutant_discord-0.1.2.dist-info/METADATA
adjutant_discord-0.1.2.dist-info/WHEEL
adjutant_discord-0.1.2.dist-info/top_level.txt
adjutant_discord-0.1.2.dist-info/RECORD
