Metadata-Version: 2.1
Name: adjutant-discord
Version: 0.1.2
Summary: A package for managing ML experiments over Discord in conjunction with WandB.
Home-page: https://github.com/kostaleonard/adjutant
Author: Leo Kosta
Author-email: kostaleonard@gmail.com
License: UNKNOWN
Project-URL: Bug Tracker, https://github.com/kostaleonard/adjutant/issues
Platform: UNKNOWN
Classifier: Programming Language :: Python :: 3
Classifier: License :: OSI Approved :: MIT License
Classifier: Operating System :: OS Independent
License-File: LICENSE
Requires-Dist: discord.py
Requires-Dist: wandb
Requires-Dist: numpy
